leafcutterITI/__init__.py
leafcutterITI/__main__.py
leafcutterITI/shared_functions.py
leafcutterITI/utils.py
leafcutterITI/clustering/__init__.py
leafcutterITI/clustering/leafcutterITI_clustering.py
leafcutterITI/clustering/utils.py
leafcutterITI/map_gen/__init__.py
leafcutterITI/map_gen/leafcutterITI_map_gen.py
leafcutterITI/scITI/__init__.py
leafcutterITI/scITI/calcutta_functions.py
leafcutterITI/scITI/leafcutterITI_scITI.py
leafcutterITI-0.2.0.dist-info/LICENSE
leafcutterITI-0.2.0.dist-info/METADATA
leafcutterITI-0.2.0.dist-info/WHEEL
leafcutterITI-0.2.0.dist-info/entry_points.txt
leafcutterITI-0.2.0.dist-info/top_level.txt
leafcutterITI-0.2.0.dist-info/RECORD
