Metadata-Version: 2.1
Name: leafcutterITI
Version: 0.2.0
Summary: LeafcutterITI implementation
Author: Xingpei Zhang, David A Knowles
License: MIT License
Project-URL: Homepage, https://github.com/XZ3149/LeafcutterITI
Requires-Python: >=3.8
License-File: LICENSE
Requires-Dist: numpy
Requires-Dist: pyranges
Requires-Dist: pandas
Requires-Dist: scipy
